odoo/addons/account_early_payment_discount/README.rst
odoo/addons/account_early_payment_discount/__init__.py
odoo/addons/account_early_payment_discount/__manifest__.py
odoo/addons/account_early_payment_discount/docs/payment_term_form.png
odoo/addons/account_early_payment_discount/models/__init__.py
odoo/addons/account_early_payment_discount/models/account_payment_term.py
odoo/addons/account_early_payment_discount/tests/__init__.py
odoo/addons/account_early_payment_discount/tests/test_payment_term.py
odoo/addons/account_early_payment_discount/views/account_payment_term.xml
odoo11_addon_account_early_payment_discount-11.0.1.0.0.dist-info/DESCRIPTION.rst
odoo11_addon_account_early_payment_discount-11.0.1.0.0.dist-info/METADATA
odoo11_addon_account_early_payment_discount-11.0.1.0.0.dist-info/RECORD
odoo11_addon_account_early_payment_discount-11.0.1.0.0.dist-info/WHEEL
odoo11_addon_account_early_payment_discount-11.0.1.0.0.dist-info/metadata.json
odoo11_addon_account_early_payment_discount-11.0.1.0.0.dist-info/top_level.txt
